pypanuclei/pypanuclei.py
pypanuclei-0.1.dist-info/METADATA
pypanuclei-0.1.dist-info/WHEEL
pypanuclei-0.1.dist-info/entry_points.txt
pypanuclei-0.1.dist-info/licenses/LICENSE
pypanuclei-0.1.dist-info/RECORD
