Metadata-Version: 2.1
Name: pypanuclei
Version: 0.1
Summary: pypanuclei (Python Passive Nuclei), it's a replace for nuclei passive scanner
Project-URL: Homepage, https://github.com/rivalsec/pypanuclei
Project-URL: Bug Tracker, https://github.com/rivalsec/pypanuclei/issues
Author: Vladimir Sopernikov
License-File: LICENSE
Classifier: License :: OSI Approved :: MIT License
Classifier: Operating System :: OS Independent
Classifier: Programming Language :: Python :: 3
Requires-Python: >=3.7
